fastapi_sqlalchemy/__init__.py
fastapi_sqlalchemy/decorators.py
fastapi_sqlalchemy/exceptions.py
fastapi_sqlalchemy/extensions.py
fastapi_sqlalchemy/middleware.py
fastapi_sqlalchemy/py.typed
fastapi_sqlalchemy/sqlalchemy_types.py
fastapi_sqlalchemy/types.py
FastAPI_SQLAlchemy_improved-0.5.0.dist-info/LICENSE
FastAPI_SQLAlchemy_improved-0.5.0.dist-info/METADATA
FastAPI_SQLAlchemy_improved-0.5.0.dist-info/WHEEL
FastAPI_SQLAlchemy_improved-0.5.0.dist-info/top_level.txt
FastAPI_SQLAlchemy_improved-0.5.0.dist-info/RECORD
